{"word_count": 2861, "processed_language": "en", "personality": [{"trait_id": "big5_openness", "name": "Openness", "category": "personality", "percentile": 0.6915337219771163, "significant": true, "children": [{"trait_id": "facet_adventurousness", "name": "Adventurousness", "category": "personality", "percentile": 0.41194192725032447, "significant": true}, {"trait_id": "facet_artistic_interests", "name": "Artistic interests", "category": "personality", "percentile": 0.5820968410123205, "significant": true}, {"trait_id": "facet_emotionality", "name": "Emotionality", "category": "personality", "percentile": 0.7609322366229865, "significant": true}, {"trait_id": "facet_imagination", "name": "Imagination", "category": "personality", "percentile": 0.6719265154163238, "significant": true}, {"trait_id": "facet_intellect", "name": "Intellect", "category": "personality", "percentile": 0.9681655481555247, "significant": true}, {"trait_id": "facet_liberalism", "name": "Authority-challenging", "category": "personality", "percentile": 0.9514055115208895, "significant": true}]}, {"trait_id": "big5_conscientiousness", "name": "Conscientiousness", "category": "personality", "percentile": 0.25381997246548754, "significant": true, "children": [{"trait_id": "facet_achievement_striving", "name": "Achievement striving", "category": "personality", "percentile": 0.48163244806154754, "significant": true}, {"trait_id": "facet_cautiousness", "name": "Cautiousness", "category": "personality", "percentile": 0.7267929401234067, "significant": true}, {"trait_id": "facet_dutifulness", "name": "Dutifulness", "category": "personality", "percentile": 0.5838622982541558, "significant": true}, {"trait_id": "facet_orderliness", "name": "Orderliness", "category": "personality", "percentile": 0.10764301796173659, "significant": true}, {"trait_id": "facet_self_discipline", "name": "Self-discipline", "category": "personality", "percentile": 0.30628656323707815, "significant": true}, {"trait_id": "facet_self_efficacy", "name": "Self-efficacy", "category": "personality", "percentile": 0.44629284904810407, "significant": true}]}, {"trait_id": "big5_extraversion", "name": "Extraversion", "category": "personality", "percentile": 0.23155939370262985, "significant": true, "children": [{"trait_id": "facet_activity_level", "name": "Activity level", "category": "personality", "percentile": 0.3139578010529275, "significant": true}, {"trait_id": "facet_assertiveness", "name": "Assertiveness", "category": "personality", "percentile": 0.42911273549823375, "significant": true}, {"trait_id": "facet_cheerfulness", "name": "Cheerfulness", "category": "personality", "percentile": 0.05680145569011047, "significant": true}, {"trait_id": "facet_excitement_seeking", "name": "Excitement-seeking", "category": "personality", "percentile": 0.22796077116195246, "significant": true}, {"trait_id": "facet_friendliness", "name": "Outgoing", "category": "personality", "percentile": 0.10231738510052901, "significant": true}, {"trait_id": "facet_gregariousness", "name": "Gregariousness", "category": "personality", "percentile": 0.021420297706406688, "significant": true}]}, {"trait_id": "big5_agreeableness", "name": "Agreeableness", "category": "personality", "percentile": 0.45757906977543683, "significant": true, "children": [{"trait_id": "facet_altruism", "name": "Altruism", "category": "personality", "percentile": 0.5883928474888376, "significant": true}, {"trait_id": "facet_cooperation", "name": "Cooperation", "category": "personality", "percentile": 0.4825698864872773, "significant": true}, {"trait_id": "facet_modesty", "name": "Modesty", "category": "personality", "percentile": 0.5895762409673417, "significant": true}, {"trait_id": "facet_morality", "name": "Uncompromising", "category": "personality", "percentile": 0.5322622481127159, "significant": true}, {"trait_id": "facet_sympathy", "name": "Sympathy", "category": "personality", "percentile": 0.939098266706279, "significant": true}, {"trait_id": "facet_trust", "name": "Trust", "category": "personality", "percentile": 0.30591359749548497, "significant": true}]}, {"trait_id": "big5_neuroticism", "name": "Emotional range", "category": "personality", "percentile": 0.17338911758578307, "significant": true, "children": [{"trait_id": "facet_anger", "name": "Fiery", "category": "personality", "percentile": 0.8543751020076757, "significant": true}, {"trait_id": "facet_anxiety", "name": "Prone to worry", "category": "personality", "percentile": 0.782796282709067, "significant": true}, {"trait_id": "facet_depression", "name": "Melancholy", "category": "personality", "percentile": 0.8387347076797343, "significant": true}, {"trait_id": "facet_immoderation", "name": "Immoderation", "category": "personality", "percentile": 0.46477947047402096, "significant": true}, {"trait_id": "facet_self_consciousness", "name": "Self-consciousness", "category": "personality", "percentile": 0.896289699208895, "significant": true}, {"trait_id": "facet_vulnerability", "name": "Susceptible to stress", "category": "personality", "percentile": 0.7916664581200048, "significant": true}]}], "needs": [{"trait_id": "need_challenge", "name": "Challenge", "category": "needs", "percentile": 0.18130681405088234, "significant": true}, {"trait_id": "need_closeness", "name": "Closeness", "category": "needs", "percentile": 0.15952953662990044, "significant": true}, {"trait_id": "need_curiosity", "name": "Curiosity", "category": "needs", "percentile": 0.6044328562267346, "significant": true}, {"trait_id": "need_excitement", "name": "Excitement", "category": "needs", "percentile": 0.07976315056876343, "significant": true}, {"trait_id": "need_harmony", "name": "Harmony", "category": "needs", "percentile": 0.1946938117550554, "significant": true}, {"trait_id": "need_ideal", "name": "Ideal", "category": "needs", "percentile": 0.3225487868526183, "significant": true}, {"trait_id": "need_liberty", "name": "Liberty", "category": "needs", "percentile": 0.0766222930079779, "significant": true}, {"trait_id": "need_love", "name": "Love", "category": "needs", "percentile": 0.2005378042249351, "significant": true}, {"trait_id": "need_practicality", "name": "Practicality", "category": "needs", "percentile": 0.19940195964861518, "significant": true}, {"trait_id": "need_self_expression", "name": "Self-expression", "category": "needs", "percentile": 0.3146270125010861, "significant": true}, {"trait_id": "need_stability", "name": "Stability", "category": "needs", "percentile": 0.11337098097659337, "significant": true}, {"trait_id": "need_structure", "name": "Structure", "category": "needs", "percentile": 0.22858189928024636, "significant": true}], "values": [{"trait_id": "value_conservation", "name": "Conservation", "category": "values", "percentile": 0.07540852224738381, "significant": true}, {"trait_id": "value_openness_to_change", "name": "Openness to change", "category": "values", "percentile": 0.12462011787916416, "significant": true}, {"trait_id": "value_hedonism", "name": "Hedonism", "category": "values", "percentile": 0.17398884151597754, "significant": true}, {"trait_id": "value_self_enhancement", "name": "Self-enhancement", "category": "values", "percentile": 0.3231118965012525, "significant": true}, {"trait_id": "value_self_transcendence", "name": "Self-transcendence", "category": "values", "percentile": 0.3512177646215976, "significant": true}], "warnings": []}