{"word_count": 2562, "processed_language": "en", "personality": [{"trait_id": "big5_openness", "name": "Openness", "category": "personality", "percentile": 0.2895642312095469, "significant": true, "children": [{"trait_id": "facet_adventurousness", "name": "Adventurousness", "category": "personality", "percentile": 0.0502180706287737, "significant": true}, {"trait_id": "facet_artistic_interests", "name": "Artistic interests", "category": "personality", "percentile": 0.9604908359825353, "significant": true}, {"trait_id": "facet_emotionality", "name": "Emotionality", "category": "personality", "percentile": 0.9986100770264408, "significant": true}, {"trait_id": "facet_imagination", "name": "Imagination", "category": "personality", "percentile": 0.8378382917358882, "significant": true}, {"trait_id": "facet_intellect", "name": "Intellect", "category": "personality", "percentile": 0.33708977292047004, "significant": true}, {"trait_id": "facet_liberalism", "name": "Authority-challenging", "category": "personality", "percentile": 0.14823893890079132, "significant": true}]}, {"trait_id": "big5_conscientiousness", "name": "Conscientiousness", "category": "personality", "percentile": 0.8831996379078152, "significant": true, "children": [{"trait_id": "facet_achievement_striving", "name": "Achievement striving", "category": "personality", "percentile": 0.9648497597496803, "significant": true}, {"trait_id": "facet_cautiousness", "name": "Cautiousness", "category": "personality", "percentile": 0.3436675883205719, "significant": true}, {"trait_id": "facet_dutifulness", "name": "Dutifulness", "category": "personality", "percentile": 0.9701106567977382, "significant": true}, {"trait_id": "facet_orderliness", "name": "Orderliness", "category": "personality", "percentile": 0.3030150719680972, "significant": true}, {"trait_id": "facet_self_discipline", "name": "Self-discipline", "category": "personality", "percentile": 0.6838209921111356, "significant": true}, {"trait_id": "facet_self_efficacy", "name": "Self-efficacy", "category": "personality", "percentile": 0.7262310709479393, "significant": true}]}, {"trait_id": "big5_extraversion", "name": "Extraversion", "category": "personality", "percentile": 0.9633828691307629, "significant": true, "children": [{"trait_id": "facet_activity_level", "name": "Activity level", "category": "personality", "percentile": 0.8991506657948105, "significant": true}, {"trait_id": "facet_assertiveness", "name": "Assertiveness", "category": "personality", "percentile": 0.5235182987875737, "significant": true}, {"trait_id": "facet_cheerfulness", "name": "Cheerfulness", "category": "personality", "percentile": 0.998988007284769, "significant": true}, {"trait_id": "facet_excitement_seeking", "name": "Excitement-seeking", "category": "personality", "percentile": 0.4696914273251006, "significant": true}, {"trait_id": "facet_friendliness", "name": "Outgoing", "category": "personality", "percentile": 0.883983147738121, "significant": true}, {"trait_id": "facet_gregariousness", "name": "Gregariousness", "category": "personality", "percentile": 0.712493734851244, "significant": true}]}, {"trait_id": "big5_agreeableness", "name": "Agreeableness", "category": "personality", "percentile": 0.9996848010342767, "significant": true, "children": [{"trait_id": "facet_altruism", "name": "Altruism", "category": "personality", "percentile": 0.9998945047150122, "significant": true}, {"trait_id": "facet_cooperation", "name": "Cooperation", "category": "personality", "percentile": 0.9725516030747824, "significant": true}, {"trait_id": "facet_modesty", "name": "Modesty", "category": "personality", "percentile": 0.9311573861285394, "significant": true}, {"trait_id": "facet_morality", "name": "Uncompromising", "category": "personality", "percentile": 0.9643051047557716, "significant": true}, {"trait_id": "facet_sympathy", "name": "Sympathy", "category": "personality", "percentile": 0.9990507423767296, "significant": true}, {"trait_id": "facet_trust", "name": "Trust", "category": "personality", "percentile": 0.9545815266134592, "significant": true}]}, {"trait_id": "big5_neuroticism", "name": "Emotional range", "category": "personality", "percentile": 0.6473278782250693, "significant": true, "children": [{"trait_id": "facet_anger", "name": "Fiery", "category": "personality", "percentile": 0.554253100030032, "significant": true}, {"trait_id": "facet_anxiety", "name": "Prone to worry", "category": "personality", "percentile": 0.698091067516002, "significant": true}, {"trait_id": "facet_depression", "name": "Melancholy", "category": "personality", "percentile": 0.6499132831804811, "significant": true}, {"trait_id": "facet_immoderation", "name": "Immoderation", "category": "personality", "percentile": 0.07373837466289934, "significant": true}, {"trait_id": "facet_self_consciousness", "name": "Self-consciousness", "category": "personality", "percentile": 0.32387651774378484, "significant": true}, {"trait_id": "facet_vulnerability", "name": "Susceptible to stress", "category": "personality", "percentile": 0.8422804121325329, "significant": true}]}], "needs": [{"trait_id": "need_challenge", "name": "Challenge", "category": "needs", "percentile": 0.3435537723203702, "significant": true}, {"trait_id": "need_closeness", "name": "Closeness", "category": "needs", "percentile": 0.9846010379766121, "significant": true}, {"trait_id": "need_curiosity", "name": "Curiosity", "category": "needs", "percentile": 0.7548224006875153, "significant": true}, {"trait_id": "need_excitement", "name": "Excitement", "category": "needs", "percentile": 0.2763261187694154, "significant": true}, {"trait_id": "need_harmony", "name": "Harmony", "category": "needs", "percentile": 0.9820423861495537, "significant": true}, {"trait_id": "need_ideal", "name": "Ideal", "category": "needs", "percentile": 0.6667409230094435, "significant": true}, {"trait_id": "need_liberty", "name": "Liberty", "category": "needs", "percentile": 0.7013445417980411, "significant": true}, {"trait_id": "need_love", "name": "Love", "category": "needs", "percentile": 0.8524817717641868, "significant": true}, {"trait_id": "need_practicality", "name": "Practicality", "category": "needs", "percentile": 0.019064227040844706, "significant": true}, {"trait_id": "need_self_expression", "name": "Self-expression", "category": "needs", "percentile": 0.5955618314565261, "significant": true}, {"trait_id": "need_stability", "name": "Stability", "category": "needs", "percentile": 0.7748805807817948, "significant": true}, {"trait_id": "need_structure", "name": "Structure", "category": "needs", "percentile": 0.14117708041731158, "significant": true}], "values": [{"trait_id": "value_conservation", "name": "Conservation", "category": "values", "percentile": 0.9602768355331743, "significant": true}, {"trait_id": "value_openness_to_change", "name": "Openness to change", "category": "values", "percentile": 0.2579997619353722, "significant": true}, {"trait_id": "value_hedonism", "name": "Hedonism", "category": "values", "percentile": 0.33689199749940923, "significant": true}, {"trait_id": "value_self_enhancement", "name": "Self-enhancement", "category": "values", "percentile": 0.36139600103124736, "significant": true}, {"trait_id": "value_self_transcendence", "name": "Self-transcendence", "category": "values", "percentile": 0.841005985479961, "significant": true}], "warnings": []}