{"word_count": 2973, "processed_language": "en", "personality": [{"trait_id": "big5_openness", "name": "Openness", "category": "personality", "percentile": 0.9434389883821706, "significant": true, "children": [{"trait_id": "facet_adventurousness", "name": "Adventurousness", "category": "personality", "percentile": 0.980864752276488, "significant": true}, {"trait_id": "facet_artistic_interests", "name": "Artistic interests", "category": "personality", "percentile": 0.8186906730820511, "significant": true}, {"trait_id": "facet_emotionality", "name": "Emotionality", "category": "personality", "percentile": 0.25466820438662946, "significant": true}, {"trait_id": "facet_imagination", "name": "Imagination", "category": "personality", "percentile": 0.8334985396128842, "significant": true}, {"trait_id": "facet_intellect", "name": "Intellect", "category": "personality", "percentile": 0.9549773428831874, "significant": true}, {"trait_id": "facet_liberalism", "name": "Authority-challenging", "category": "personality", "percentile": 0.9732972449420398, "significant": true}]}, {"trait_id": "big5_conscientiousness", "name": "Conscientiousness", "category": "personality", "percentile": 0.5854715659646804, "significant": true, "children": [{"trait_id": "facet_achievement_striving", "name": "Achievement striving", "category": "personality", "percentile": 0.7996708465526458, "significant": true}, {"trait_id": "facet_cautiousness", "name": "Cautiousness", "category": "personality", "percentile": 0.737026253509049, "significant": true}, {"trait_id": "facet_dutifulness", "name": "Dutifulness", "category": "personality", "percentile": 0.3923228195807547, "significant": true}, {"trait_id": "facet_orderliness", "name": "Orderliness", "category": "personality", "percentile": 0.3939122735025925, "significant": true}, {"trait_id": "facet_self_discipline", "name": "Self-discipline", "category": "personality", "percentile": 0.5830781287031916, "significant": true}, {"trait_id": "facet_self_efficacy", "name": "Self-efficacy", "category": "personality", "percentile": 0.7974972910840362, "significant": true}]}, {"trait_id": "big5_extraversion", "name": "Extraversion", "category": "personality", "percentile": 0.5422818074878365, "significant": true, "children": [{"trait_id": "facet_activity_level", "name": "Activity level", "category": "personality", "percentile": 0.9711481285180973, "significant": true}, {"trait_id": "facet_assertiveness", "name": "Assertiveness", "category": "personality", "percentile": 0.9245872264053945, "significant": true}, {"trait_id": "facet_cheerfulness", "name": "Cheerfulness", "category": "personality", "percentile": 0.19076735265174355, "significant": true}, {"trait_id": "facet_excitement_seeking", "name": "Excitement-seeking", "category": "personality", "percentile": 0.5635198108967396, "significant": true}, {"trait_id": "facet_friendliness", "name": "Outgoing", "category": "personality", "percentile": 0.4056410995863602, "significant": true}, {"trait_id": "facet_gregariousness", "name": "Gregariousness", "category": "personality", "percentile": 0.2527062600538078, "significant": true}]}, {"trait_id": "big5_agreeableness", "name": "Agreeableness", "category": "personality", "percentile": 0.07697714522912902, "significant": true, "children": [{"trait_id": "facet_altruism", "name": "Altruism", "category": "personality", "percentile": 0.6971953266136018, "significant": true}, {"trait_id": "facet_cooperation", "name": "Cooperation", "category": "personality", "percentile": 0.7163888718504177, "significant": true}, {"trait_id": "facet_modesty", "name": "Modesty", "category": "personality", "percentile": 0.01990512010875828, "significant": true}, {"trait_id": "facet_morality", "name": "Uncompromising", "category": "personality", "percentile": 0.27235211046190444, "significant": true}, {"trait_id": "facet_sympathy", "name": "Sympathy", "category": "personality", "percentile": 0.3809009511317396, "significant": true}, {"trait_id": "facet_trust", "name": "Trust", "category": "personality", "percentile": 0.950818851640673, "significant": true}]}, {"trait_id": "big5_neuroticism", "name": "Emotional range", "category": "personality", "percentile": 0.5274221709278841, "significant": true, "children": [{"trait_id": "facet_anger", "name": "Fiery", "category": "personality", "percentile": 0.09828757579915137, "significant": true}, {"trait_id": "facet_anxiety", "name": "Prone to worry", "category": "personality", "percentile": 0.3262886006849537, "significant": true}, {"trait_id": "facet_depression", "name": "Melancholy", "category": "personality", "percentile": 0.30149467278351016, "significant": true}, {"trait_id": "facet_immoderation", "name": "Immoderation", "category": "personality", "percentile": 0.05953968834661777, "significant": true}, {"trait_id": "facet_self_consciousness", "name": "Self-consciousness", "category": "personality", "percentile": 0.4793192752110873, "significant": true}, {"trait_id": "facet_vulnerability", "name": "Susceptible to stress", "category": "personality", "percentile": 0.19118899848672394, "significant": true}]}], "needs": [{"trait_id": "need_challenge", "name": "Challenge", "category": "needs", "percentile": 0.8231785065712003, "significant": true}, {"trait_id": "need_closeness", "name": "Closeness", "category": "needs", "percentile": 0.07947309949674952, "significant": true}, {"trait_id": "need_curiosity", "name": "Curiosity", "category": "needs", "percentile": 0.8562605004449103, "significant": true}, {"trait_id": "need_excitement", "name": "Excitement", "category": "needs", "percentile": 0.3318731447862809, "significant": true}, {"trait_id": "need_harmony", "name": "Harmony", "category": "needs", "percentile": 0.3491103993982899, "significant": true}, {"trait_id": "need_ideal", "name": "Ideal", "category": "needs", "percentile": 0.47958026085299077, "significant": true}, {"trait_id": "need_liberty", "name": "Liberty", "category": "needs", "percentile": 0.5752189797133225, "significant": true}, {"trait_id": "need_love", "name": "Love", "category": "needs", "percentile": 0.46783189056304736, "significant": true}, {"trait_id": "need_practicality", "name": "Practicality", "category": "needs", "percentile": 0.8153950866052481, "significant": true}, {"trait_id": "need_self_expression", "name": "Self-expression", "category": "needs", "percentile": 0.7238793521408318, "significant": true}, {"trait_id": "need_stability", "name": "Stability", "category": "needs", "percentile": 0.23845886557690332, "significant": true}, {"trait_id": "need_structure", "name": "Structure", "category": "needs", "percentile": 0.6138896723657598, "significant": true}], "values": [{"trait_id": "value_conservation", "name": "Conservation", "category": "values", "percentile": 0.05066194199449997, "significant": true}, {"trait_id": "value_openness_to_change", "name": "Openness to change", "category": "values", "percentile": 0.7742370632132645, "significant": true}, {"trait_id": "value_hedonism", "name": "Hedonism", "category": "values", "percentile": 0.24718535398879649, "significant": true}, {"trait_id": "value_self_enhancement", "name": "Self-enhancement", "category": "values", "percentile": 0.7641373886102862, "significant": true}, {"trait_id": "value_self_transcendence", "name": "Self-transcendence", "category": "values", "percentile": 0.20647086917952462, "significant": true}], "warnings": []}