{"word_count": 2956, "processed_language": "en", "personality": [{"trait_id": "big5_openness", "name": "Openness", "category": "personality", "percentile": 0.04141241703142118, "significant": true, "children": [{"trait_id": "facet_adventurousness", "name": "Adventurousness", "category": "personality", "percentile": 0.16402450912878425, "significant": true}, {"trait_id": "facet_artistic_interests", "name": "Artistic interests", "category": "personality", "percentile": 0.5857922500406668, "significant": true}, {"trait_id": "facet_emotionality", "name": "Emotionality", "category": "personality", "percentile": 0.6065801429643203, "significant": true}, {"trait_id": "facet_imagination", "name": "Imagination", "category": "personality", "percentile": 0.8924904422605455, "significant": true}, {"trait_id": "facet_intellect", "name": "Intellect", "category": "personality", "percentile": 0.03674893499287124, "significant": true}, {"trait_id": "facet_liberalism", "name": "Authority-challenging", "category": "personality", "percentile": 0.06769426427913344, "significant": true}]}, {"trait_id": "big5_conscientiousness", "name": "Conscientiousness", "category": "personality", "percentile": 0.6043394279164619, "significant": true, "children": [{"trait_id": "facet_achievement_striving", "name": "Achievement striving", "category": "personality", "percentile": 0.48690325995961037, "significant": true}, {"trait_id": "facet_cautiousness", "name": "Cautiousness", "category": "personality", "percentile": 0.23123715157092062, "significant": true}, {"trait_id": "facet_dutifulness", "name": "Dutifulness", "category": "personality", "percentile": 0.3624174412919828, "significant": true}, {"trait_id": "facet_orderliness", "name": "Orderliness", "category": "personality", "percentile": 0.6863182913105565, "significant": true}, {"trait_id": "facet_self_discipline", "name": "Self-discipline", "category": "personality", "percentile": 0.31064158343072923, "significant": true}, {"trait_id": "facet_self_efficacy", "name": "Self-efficacy", "category": "personality", "percentile": 0.7339060710770202, "significant": true}]}, {"trait_id": "big5_extraversion", "name": "Extraversion", "category": "personality", "percentile": 0.16991956912190764, "significant": true, "children": [{"trait_id": "facet_activity_level", "name": "Activity level", "category": "personality", "percentile": 0.7710882883275357, "significant": true}, {"trait_id": "facet_assertiveness", "name": "Assertiveness", "category": "personality", "percentile": 0.6291889048161206, "significant": true}, {"trait_id": "facet_cheerfulness", "name": "Cheerfulness", "category": "personality", "percentile": 0.7706931845319278, "significant": true}, {"trait_id": "facet_excitement_seeking", "name": "Excitement-seeking", "category": "personality", "percentile": 0.858837292995521, "significant": true}, {"trait_id": "facet_friendliness", "name": "Outgoing", "category": "personality", "percentile": 0.3474213229109746, "significant": true}, {"trait_id": "facet_gregariousness", "name": "Gregariousness", "category": "personality", "percentile": 0.4607158873373831, "significant": true}]}, {"trait_id": "big5_agreeableness", "name": "Agreeableness", "category": "personality", "percentile": 0.8659353435117931, "significant": true, "children": [{"trait_id": "facet_altruism", "name": "Altruism", "category": "personality", "percentile": 0.645589683546083, "significant": true}, {"trait_id": "facet_cooperation", "name": "Cooperation", "category": "personality", "percentile": 0.3940257059165486, "significant": true}, {"trait_id": "facet_modesty", "name": "Modesty", "category": "personality", "percentile": 0.5654842031134166, "significant": true}, {"trait_id": "facet_morality", "name": "Uncompromising", "category": "personality", "percentile": 0.2986662257399541, "significant": true}, {"trait_id": "facet_sympathy", "name": "Sympathy", "category": "personality", "percentile": 0.7186667258635815, "significant": true}, {"trait_id": "facet_trust", "name": "Trust", "category": "personality", "percentile": 0.8154149986706479, "significant": true}]}, {"trait_id": "big5_neuroticism", "name": "Emotional range", "category": "personality", "percentile": 0.2538138411540063, "significant": true, "children": [{"trait_id": "facet_anger", "name": "Fiery", "category": "personality", "percentile": 0.6923046808531136, "significant": true}, {"trait_id": "facet_anxiety", "name": "Prone to worry", "category": "personality", "percentile": 0.8291607640077447, "significant": true}, {"trait_id": "facet_depression", "name": "Melancholy", "category": "personality", "percentile": 0.6933495760931677, "significant": true}, {"trait_id": "facet_immoderation", "name": "Immoderation", "category": "personality", "percentile": 0.014753405748483495, "significant": true}, {"trait_id": "facet_self_consciousness", "name": "Self-consciousness", "category": "personality", "percentile": 0.7529611494193185, "significant": true}, {"trait_id": "facet_vulnerability", "name": "Susceptible to stress", "category": "personality", "percentile": 0.7788810070490366, "significant": true}]}], "needs": [{"trait_id": "need_challenge", "name": "Challenge", "category": "needs", "percentile": 0.6798547017672963, "significant": true}, {"trait_id": "need_closeness", "name": "Closeness", "category": "needs", "percentile": 0.9700295318883757, "significant": true}, {"trait_id": "need_curiosity", "name": "Curiosity", "category": "needs", "percentile": 0.9322300589285601, "significant": true}, {"trait_id": "need_excitement", "name": "Excitement", "category": "needs", "percentile": 0.7676249075129848, "significant": true}, {"trait_id": "need_harmony", "name": "Harmony", "category": "needs", "percentile": 0.9922155496965803, "significant": true}, {"trait_id": "need_ideal", "name": "Ideal", "category": "needs", "percentile": 0.9921809953420706, "significant": true}, {"trait_id": "need_liberty", "name": "Liberty", "category": "needs", "percentile": 0.9443534640155202, "significant": true}, {"trait_id": "need_love", "name": "Love", "category": "needs", "percentile": 0.9343756190511571, "significant": true}, {"trait_id": "need_practicality", "name": "Practicality", "category": "needs", "percentile": 0.5568836621722442, "significant": true}, {"trait_id": "need_self_expression", "name": "Self-expression", "category": "needs", "percentile": 0.9455521392869677, "significant": true}, {"trait_id": "need_stability", "name": "Stability", "category": "needs", "percentile": 0.9795711938188033, "significant": true}, {"trait_id": "need_structure", "name": "Structure", "category": "needs", "percentile": 0.6772099203972928, "significant": true}], "values": [{"trait_id": "value_conservation", "name": "Conservation", "category": "values", "percentile": 0.9638228478007941, "significant": true}, {"trait_id": "value_openness_to_change", "name": "Openness to change", "category": "values", "percentile": 0.626741369554311, "significant": true}, {"trait_id": "value_hedonism", "name": "Hedonism", "category": "values", "percentile": 0.8617760760836854, "significant": true}, {"trait_id": "value_self_enhancement", "name": "Self-enhancement", "category": "values", "percentile": 0.8655797892239062, "significant": true}, {"trait_id": "value_self_transcendence", "name": "Self-transcendence", "category": "values", "percentile": 0.5894877426761373, "significant": true}], "warnings": []}